dbt_meta/__init__.py
dbt_meta/cli.py
dbt_meta/commands.py
dbt_meta/config.py
dbt_meta/errors.py
dbt_meta/fallback.py
dbt_meta/catalog/__init__.py
dbt_meta/catalog/parser.py
dbt_meta/command_impl/__init__.py
dbt_meta/command_impl/base.py
dbt_meta/command_impl/children.py
dbt_meta/command_impl/columns.py
dbt_meta/command_impl/config.py
dbt_meta/command_impl/deps.py
dbt_meta/command_impl/info.py
dbt_meta/command_impl/lineage_utils.py
dbt_meta/command_impl/parents.py
dbt_meta/command_impl/path.py
dbt_meta/command_impl/schema.py
dbt_meta/command_impl/sql.py
dbt_meta/manifest/__init__.py
dbt_meta/manifest/finder.py
dbt_meta/manifest/parser.py
dbt_meta/templates/dbt-meta.toml
dbt_meta/utils/__init__.py
dbt_meta/utils/bigquery.py
dbt_meta/utils/dev.py
dbt_meta/utils/git.py
dbt_meta/utils/model_state.py
dbt_meta-0.2.0.dist-info/METADATA
dbt_meta-0.2.0.dist-info/WHEEL
dbt_meta-0.2.0.dist-info/entry_points.txt
dbt_meta-0.2.0.dist-info/licenses/LICENSE
dbt_meta-0.2.0.dist-info/RECORD
