Metadata-Version: 2.4
Name: dbt-meta
Version: 0.2.0
Summary: AI-first CLI for dbt metadata extraction - Fast, modern Python tool
Project-URL: Homepage, https://github.com/Filianin/dbt-meta
Project-URL: Repository, https://github.com/Filianin/dbt-meta
Project-URL: Changelog, https://github.com/Filianin/dbt-meta/blob/main/CHANGELOG.md
Author: Pavel Filianin
License: Apache-2.0
License-File: LICENSE
Keywords: ai,analytics,bigquery,cli,dbt,metadata
Classifier: Development Status :: 4 - Beta
Classifier: Intended Audience :: Developers
Classifier: License :: OSI Approved :: Apache Software License
Classifier: Programming Language :: Python :: 3
Classifier: Programming Language :: Python :: 3.9
Classifier: Programming Language :: Python :: 3.10
Classifier: Programming Language :: Python :: 3.11
Classifier: Programming Language :: Python :: 3.12
Classifier: Topic :: Software Development :: Libraries :: Python Modules
Requires-Python: >=3.9
Requires-Dist: orjson>=3.10.0
Requires-Dist: tomli>=2.0.0; python_version < '3.11'
Requires-Dist: typer[all]>=0.12.0
Requires-Dist: watchfiles>=0.21.0
Provides-Extra: dev
Requires-Dist: mypy>=1.8.0; extra == 'dev'
Requires-Dist: pytest-benchmark>=4.0.0; extra == 'dev'
Requires-Dist: pytest-cov>=4.1.0; extra == 'dev'
Requires-Dist: pytest-mock>=3.12.0; extra == 'dev'
Requires-Dist: pytest>=8.0.0; extra == 'dev'
Requires-Dist: ruff>=0.8.0; extra == 'dev'
